.gitignore
.project
CHANGES.txt
COPYRIGHT.txt
LICENSE.txt
README.txt
buildout.cfg
setup.cfg
setup.py
src/.project
src/pyramid_oauth2_client/__init__.py
src/pyramid_oauth2_client/abstract.py
src/pyramid_oauth2_client/facebook.py
src/pyramid_oauth2_client/yasso.py
src/pyramid_oauth2_client.egg-info/PKG-INFO
src/pyramid_oauth2_client.egg-info/SOURCES.txt
src/pyramid_oauth2_client.egg-info/dependency_links.txt
src/pyramid_oauth2_client.egg-info/not-zip-safe
src/pyramid_oauth2_client.egg-info/requires.txt
src/pyramid_oauth2_client.egg-info/top_level.txt