Metadata-Version: 1.0
Name: pyramid-oauth2-client
Version: 0.1
Summary: Library for authenticating Pyramid apps using OAuth2
Home-page: https://github.com/hathawsh/pyramid_oauth2_client
Author: Shane Hathaway
Author-email: shane@hathawaymix.org
License: BSD-derived (http://www.repoze.org/LICENSE.txt)
Keywords: web pylons pyramid oauth oauth2 facebook yasso
Platform: UNKNOWN
Classifier: Development Status :: 3 - Alpha
Classifier: Intended Audience :: Developers
Classifier: Programming Language :: Python
Classifier: Framework :: Pylons
Classifier: Topic :: Internet :: WWW/HTTP
